LICENSE
README.md
setup.py
CryptoPwd/__init__.py
CryptoPwd/crypt.py
encryptPack.egg-info/PKG-INFO
encryptPack.egg-info/SOURCES.txt
encryptPack.egg-info/dependency_links.txt
encryptPack.egg-info/requires.txt
encryptPack.egg-info/top_level.txt