Metadata-Version: 2.1
Name: encryptPack
Version: 1.1.6
Summary: Pacote para geração e criptografia de senhas, criptografia e descriptografia de arquivos
Home-page: https://github.com/NaraAndrad3/crypto
Author: Nara Raquel e Vinicius Nunes
Author-email: naradiasspn1967@gmail.com
Maintainer: Vinicius Nunes
Maintainer-email: viniciusnunes02612@gmail.com
License: MIT License
Keywords: Password
Platform: UNKNOWN
License-File: LICENSE
